LICENSE.txt
MANIFEST.in
README.md
setup.cfg
setup.py
opensecrets_api/__init__.py
opensecrets_api.egg-info/PKG-INFO
opensecrets_api.egg-info/SOURCES.txt
opensecrets_api.egg-info/dependency_links.txt
opensecrets_api.egg-info/not-zip-safe
opensecrets_api.egg-info/requires.txt
opensecrets_api.egg-info/top_level.txt